kacl.py
kacl-0.1.8.dist-info/entry_points.txt
kacl-0.1.8.dist-info/WHEEL
kacl-0.1.8.dist-info/METADATA
kacl-0.1.8.dist-info/RECORD
