Metadata-Version: 2.3
Name: kacl
Version: 0.1.8
Summary: Generate and maintain a changelog from Git commits.
Author-email: Daniel Rocha <daniel@rocha.io>
Requires-Python: >=3.13
Requires-Dist: typer>=0.13.0
